arithmetipy-0.3.0.dist-info/METADATA
arithmetipy-0.3.0.dist-info/WHEEL
arithmetipy-0.3.0.dist-info/licenses/LICENSE
arithmetipy.libs/libgcc_s-0366c7ba.so.1
arithmetipy/__init__.py
arithmetipy/arithmetipy.cpython-312-arm-linux-musleabihf.so
arithmetipy-0.3.0.dist-info/RECORD
