Metadata-Version: 2.4
Name: arithmetipy
Version: 0.3.0
Classifier: Development Status :: 4 - Beta
Classifier: Intended Audience :: Developers
Classifier: License :: OSI Approved :: MIT License
Classifier: Programming Language :: Python :: 3
Classifier: Programming Language :: Python :: 3.8
Classifier: Programming Language :: Python :: 3.9
Classifier: Programming Language :: Python :: 3.10
Classifier: Programming Language :: Python :: 3.11
Classifier: Programming Language :: Python :: 3.12
Classifier: Programming Language :: Rust
Classifier: Programming Language :: Python :: Implementation :: CPython
Classifier: Programming Language :: Python :: Implementation :: PyPy
Classifier: Topic :: Software Development :: Libraries
Classifier: Topic :: System :: Archiving :: Compression
License-File: LICENSE
Summary: Python bindings for a Rust implementation of arithmetic coding (encoder/decoder).
Keywords: arithmetic coding,compression,entropy coding,rust,bindings
Author-email: Mahdi Khodabandeh <20.mahdikh.0@gmail.com>
Requires-Python: >=3.8
Project-URL: Homepage, https://github.com/khoda81/arithmetipy
Project-URL: Repository, https://github.com/khoda81/arithmetipy
Project-URL: Issues, https://github.com/khoda81/arithmetipy/issues
